dynflowparser/__init__.py
dynflowparser/bin/__init__.py
dynflowparser/html/__init__.py
dynflowparser/html/css/__init__.py
dynflowparser/html/css/dynflowparser.css
dynflowparser/html/css/jquery.treetable.css
dynflowparser/html/css/jquery.treetable.theme.default.css
dynflowparser/html/js/__init__.py
dynflowparser/html/js/dynflowparser.js
dynflowparser/html/js/jquery.js
dynflowparser/html/js/jquery.treetable.js
dynflowparser/lib/__init__.py
dynflowparser/lib/configuration.py
dynflowparser/lib/outputhtml.py
dynflowparser/lib/outputsqlite.py
dynflowparser/lib/useful_queries.py
dynflowparser/lib/util.py
dynflowparser/plugins/__init__.py
dynflowparser/plugins/blametaskexecution.py
dynflowparser/plugins/dynflowpolling.py
dynflowparser/plugins/heatstatssidekiqworkers.py
dynflowparser/plugins/pulpcore.py
dynflowparser/templates/__init__.py
dynflowparser/templates/actions.html
dynflowparser/templates/header.html
dynflowparser/templates/tasks.csv
dynflowparser/templates/tasks.html
dynflowparser-1.2.0.data/scripts/__init__.py
dynflowparser-1.2.0.dist-info/licenses/AUTHORS
dynflowparser-1.2.0.dist-info/licenses/LICENSE
dynflowparser_export_tasks/__init__.py
dynflowparser_export_tasks/bin/__init__.py
dynflowparser_export_tasks/lib/__init__.py
dynflowparser_export_tasks/lib/configuration.py
dynflowparser-1.2.0.dist-info/METADATA
dynflowparser-1.2.0.dist-info/WHEEL
dynflowparser-1.2.0.dist-info/entry_points.txt
dynflowparser-1.2.0.dist-info/top_level.txt
dynflowparser-1.2.0.dist-info/RECORD
