Metadata-Version: 2.4
Name: dynflowparser
Version: 1.2.0
Summary: Get sosreport dynflow files and generates user friendly html pages for
Home-page: https://github.com/pafernanr/dynflowparser
Author: Pablo Fernández Rodríguez
License: GPLv3
Keywords: theforeman dynflow
Classifier: Intended Audience :: Information Technology
Classifier: Intended Audience :: System Administrators
Classifier: License :: OSI Approved :: GNU General Public License v3 (GPLv3)
Classifier: Operating System :: POSIX :: Linux
Classifier: Programming Language :: Python
Classifier: Programming Language :: Python :: 3
License-File: LICENSE
License-File: AUTHORS
Dynamic: author
Dynamic: classifier
Dynamic: description
Dynamic: description-content-type
Dynamic: home-page
Dynamic: keywords
Dynamic: license
Dynamic: license-file
Dynamic: summary
